rapporteur/__init__.py
rapporteur/py.typed
rapporteur/report.py
rapporteur/slack.py
rapporteur/utils.py
rapporteur-0.1.3.dist-info/WHEEL
rapporteur-0.1.3.dist-info/METADATA
rapporteur-0.1.3.dist-info/RECORD
