Metadata-Version: 2.3
Name: rapporteur
Version: 0.1.3
Summary: Report run status and results to Slack and others
Author: Olivier Breuleux
Author-email: Olivier Breuleux <breuleux@gmail.com>
Requires-Dist: cryptography>=46.0.1
Requires-Dist: pyyaml>=6.0.2
Requires-Dist: serieux>=0.2.9
Requires-Dist: slack-sdk>=3.36.0
Requires-Python: >=3.11
